devicegen/__init__.py
devicegen/device_gen.py
devicegen/gds_parser.py
devicegen-1.0.4.dist-info/LICENSE.txt
devicegen-1.0.4.dist-info/METADATA
devicegen-1.0.4.dist-info/WHEEL
devicegen-1.0.4.dist-info/top_level.txt
devicegen-1.0.4.dist-info/RECORD
