Metadata-Version: 2.1
Name: devicegen
Version: 1.0.4
Summary: devicegen is a gated heterostructure device generator. It facilitates the creation of Gmsh mesh files corresponding to a gate geometry defined in a GDS layout text file.
Home-page: https://github.com/nanoacademic/devicegen
Author: Pericles Philippopoulos, Felix Beaudoin
Author-email: pericles@nanoacademic.com
License: GNU General Public License
Classifier: Programming Language :: Python :: 3
Classifier: Operating System :: OS Independent
Classifier: License :: OSI Approved :: GNU General Public License v3 or later (GPLv3+)
Classifier: Topic :: Scientific/Engineering
Requires-Python: >=3.6
License-File: LICENSE.txt
Requires-Dist: requests>=2.25.0
Requires-Dist: numpy
